MofanJiqiXuexiJiaocheng2017510Fix1/README.md
MofanJiqiXuexiJiaocheng2017510Fix1/__init__.py
MofanJiqiXuexiJiaocheng2017510Fix1/__main__.py
MofanJiqiXuexiJiaocheng2017510Fix1/file.epub
MofanJiqiXuexiJiaocheng2017510Fix1/index.html
MofanJiqiXuexiJiaocheng2017510Fix1/css/__init__.py
MofanJiqiXuexiJiaocheng2017510Fix1/css/annotations.css
MofanJiqiXuexiJiaocheng2017510Fix1/css/main.css
MofanJiqiXuexiJiaocheng2017510Fix1/css/normalize.css
MofanJiqiXuexiJiaocheng2017510Fix1/css/popup.css
MofanJiqiXuexiJiaocheng2017510Fix1/font/__init__.py
MofanJiqiXuexiJiaocheng2017510Fix1/font/fontello.eot
MofanJiqiXuexiJiaocheng2017510Fix1/font/fontello.svg
MofanJiqiXuexiJiaocheng2017510Fix1/font/fontello.ttf
MofanJiqiXuexiJiaocheng2017510Fix1/font/fontello.woff
MofanJiqiXuexiJiaocheng2017510Fix1/img/__init__.py
MofanJiqiXuexiJiaocheng2017510Fix1/img/annotator-glyph-sprite.png
MofanJiqiXuexiJiaocheng2017510Fix1/img/annotator-icon-sprite.png
MofanJiqiXuexiJiaocheng2017510Fix1/img/apple-touch-icon.png
MofanJiqiXuexiJiaocheng2017510Fix1/img/cancelfullscreen.png
MofanJiqiXuexiJiaocheng2017510Fix1/img/close.png
MofanJiqiXuexiJiaocheng2017510Fix1/img/fullscreen.png
MofanJiqiXuexiJiaocheng2017510Fix1/img/loader.gif
MofanJiqiXuexiJiaocheng2017510Fix1/img/menu-icon.png
MofanJiqiXuexiJiaocheng2017510Fix1/img/save.png
MofanJiqiXuexiJiaocheng2017510Fix1/img/saved.png
MofanJiqiXuexiJiaocheng2017510Fix1/img/settings-s.png
MofanJiqiXuexiJiaocheng2017510Fix1/img/settings.png
MofanJiqiXuexiJiaocheng2017510Fix1/img/star.png
MofanJiqiXuexiJiaocheng2017510Fix1/js/__init__.py
MofanJiqiXuexiJiaocheng2017510Fix1/js/epub.js
MofanJiqiXuexiJiaocheng2017510Fix1/js/epub.min.js
MofanJiqiXuexiJiaocheng2017510Fix1/js/epub.min.map
MofanJiqiXuexiJiaocheng2017510Fix1/js/hooks.min.js
MofanJiqiXuexiJiaocheng2017510Fix1/js/hooks.min.map
MofanJiqiXuexiJiaocheng2017510Fix1/js/reader.js
MofanJiqiXuexiJiaocheng2017510Fix1/js/reader.js.map
MofanJiqiXuexiJiaocheng2017510Fix1/js/reader.min.js
mofan_jiqi_xuexi_jiaocheng_2017_5_10_fix1-2024.3.3.0.dist-info/METADATA
mofan_jiqi_xuexi_jiaocheng_2017_5_10_fix1-2024.3.3.0.dist-info/WHEEL
mofan_jiqi_xuexi_jiaocheng_2017_5_10_fix1-2024.3.3.0.dist-info/entry_points.txt
mofan_jiqi_xuexi_jiaocheng_2017_5_10_fix1-2024.3.3.0.dist-info/top_level.txt
mofan_jiqi_xuexi_jiaocheng_2017_5_10_fix1-2024.3.3.0.dist-info/RECORD
